napari_timeseries_opener_plugin/__init__.py
napari_timeseries_opener_plugin/_dock_widget.py
napari_timeseries_opener_plugin/_version.py
napari_timeseries_opener_plugin/_tests/__init__.py
napari_timeseries_opener_plugin/_tests/test_dock_widget.py
napari_timeseries_opener_plugin-0.1.8.dist-info/LICENSE
napari_timeseries_opener_plugin-0.1.8.dist-info/METADATA
napari_timeseries_opener_plugin-0.1.8.dist-info/WHEEL
napari_timeseries_opener_plugin-0.1.8.dist-info/entry_points.txt
napari_timeseries_opener_plugin-0.1.8.dist-info/top_level.txt
napari_timeseries_opener_plugin-0.1.8.dist-info/RECORD
