Metadata-Version: 2.1
Name: napari-timeseries-opener-plugin
Version: 0.1.8
Summary: Simple plugin that opens separate .tif files as a 3-dimensional layer.
Home-page: https://github.com/gatoniel/napari-timeseries-opener-plugin
Author: Niklas Netter
Author-email: niknett@gmail.com
License: BSD-3-Clause
Project-URL: Bug Tracker, https://github.com/gatoniel/napari-timeseries-opener-plugin/issues
Project-URL: Documentation, https://github.com/gatoniel/napari-timeseries-opener-plugin#README.md
Project-URL: Source Code, https://github.com/gatoniel/napari-timeseries-opener-plugin
Project-URL: User Support, https://github.com/gatoniel/napari-timeseries-opener-plugin/issues
Classifier: Development Status :: 2 - Pre-Alpha
Classifier: Intended Audience :: Developers
Classifier: Framework :: napari
Classifier: Topic :: Software Development :: Testing
Classifier: Programming Language :: Python
Classifier: Programming Language :: Python :: 3
Classifier: Programming Language :: Python :: 3.7
Classifier: Programming Language :: Python :: 3.8
Classifier: Programming Language :: Python :: 3.9
Classifier: Operating System :: OS Independent
Classifier: License :: OSI Approved :: BSD License
Requires-Python: >=3.7
License-File: LICENSE
Requires-Dist: napari-plugin-engine (>=0.1.4)
Requires-Dist: numpy
Requires-Dist: qtpy
Requires-Dist: magicgui
Requires-Dist: tifffile
Requires-Dist: stardist
Requires-Dist: tensorflow
